{
  "project_info": {
    "project_number": "164306165639",
    "project_id": "fluttermvvmauth",
    "storage_bucket": "fluttermvvmauth.firebasestorage.app"
  },
  "client": [
    {
      "client_info": {
        "mobilesdk_app_id": "1:164306165639:android:3b227a85564d9132cebd22",
        "android_client_info": {
          "package_name": "com.example.complete_authentication"
        }
      },
      "oauth_client": [],
      "api_key": [
        {
          "current_key": "AIzaSyD7iE3hspyBm8r4pRSJiKAteejkMIhrFaI"
        }
      ],
      "services": {
        "appinvite_service": {
          "other_platform_oauth_client": []
        }
      }
    }
  ],
  "configuration_version": "1"
}